jamesql/__init__.py
jamesql/index.py
jamesql/query_simplifier.py
jamesql/rewriter.py
jamesql/script_lang.py
jamesql-0.3.0.dist-info/LICENSE
jamesql-0.3.0.dist-info/METADATA
jamesql-0.3.0.dist-info/WHEEL
jamesql-0.3.0.dist-info/top_level.txt
jamesql-0.3.0.dist-info/RECORD
