Metadata-Version: 2.1
Name: jamesql
Version: 0.3.0
Summary: A JameSQL database implemented in Python.
Home-page: https://github.com/capjamesg/jamesql
Author: capjamesg
Author-email: jamesg@jamesg.blog
Classifier: Programming Language :: Python :: 3
Classifier: License :: OSI Approved :: MIT License
Classifier: Operating System :: OS Independent
Requires-Python: >=3.7
License-File: LICENSE
Requires-Dist: pybmoore
Requires-Dist: pygtrie
Requires-Dist: lark
Requires-Dist: btrees
Requires-Dist: nltk
Provides-Extra: dev
Requires-Dist: flake8 ; extra == 'dev'
Requires-Dist: black ==22.3.0 ; extra == 'dev'
Requires-Dist: isort ; extra == 'dev'
Requires-Dist: twine ; extra == 'dev'
Requires-Dist: pytest ; extra == 'dev'
Requires-Dist: wheel ; extra == 'dev'
Requires-Dist: flask ; extra == 'dev'
Requires-Dist: orjson ; extra == 'dev'
Requires-Dist: tqdm ; extra == 'dev'
Requires-Dist: deepdiff ; extra == 'dev'
